naughties/__init__.py
naughties/provider.py
naughties-0.1.7.data/data/blns.json
naughties-0.1.7.dist-info/METADATA
naughties-0.1.7.dist-info/WHEEL
naughties-0.1.7.dist-info/top_level.txt
naughties-0.1.7.dist-info/RECORD
